Package2/Hamming.py
Package2/Jaccard.py
Package2/__init__.py
Package2-0.0.5.dist-info/LICENSE.txt.txt
Package2-0.0.5.dist-info/METADATA
Package2-0.0.5.dist-info/WHEEL
Package2-0.0.5.dist-info/top_level.txt
Package2-0.0.5.dist-info/RECORD
