Metadata-Version: 2.1
Name: Package2
Version: 0.0.5
Summary: Postion based Hamming Distance
Author: Anasua
Author-email: anasua@businessbrio.com
License: MIT
Classifier: Programming Language :: Python :: 3
Classifier: License :: OSI Approved :: MIT License
Classifier: Operating System :: OS Independent
License-File: LICENSE.txt.txt
